{"per_page":10,"total":73,"current":70,"data":[{"title":"吸引女生的终极秘诀 - 成真恋爱学","date":"2019-09-07T04:06:58.397Z","excerpt":"","link":"2019/吸引女生的终极秘诀 - 成真恋爱学"},{"title":"和女生熟悉之前怎么聊 - 成真恋爱学","date":"2019-09-07T04:06:58.397Z","excerpt":"","link":"2019/和女生熟悉之前怎么聊 - 成真恋爱学"},{"title":"和女生网上聊天对话实录分析 - 成真恋爱学","date":"2019-09-07T04:06:58.397Z","excerpt":"","link":"2019/和女生网上聊天对话实录分析 - 成真恋爱学"},{"title":"和女生聊这个，才会打动她 （附: 见面通知+特别澄清） - 成真恋爱学","date":"2019-09-07T04:06:58.397Z","excerpt":"","link":"2019/和女生聊这个，才会打动她 （附: 见面通知+特别澄清） - 成真恋爱学"},{"title":"在一起了如何保持对女生的吸引？ - 成真恋爱学","date":"2019-09-07T04:06:58.397Z","excerpt":"","link":"2019/在一起了如何保持对女生的吸引？ - 成真恋爱学"},{"title":"增加“性张力”的具体句子 - 成真恋爱学","date":"2019-09-07T04:06:58.397Z","excerpt":"","link":"2019/增加“性张力”的具体句子 - 成真恋爱学"},{"title":"奇葩握手礼看呆美女 - 成真恋爱学","date":"2019-09-07T04:06:58.397Z","excerpt":"","link":"2019/奇葩握手礼看呆美女 - 成真恋爱学"},{"title":"女人到底要什么？ - 成真恋爱学","date":"2019-09-07T04:06:58.397Z","excerpt":"","link":"2019/女人到底要什么？ - 成真恋爱学"},{"title":"女孩突然在QQ签名里写：“我想变胖啊！”  你回什么她会爱上你？(对话实例) - 成真恋爱学","date":"2019-09-07T04:06:58.397Z","excerpt":"","link":"2019/女孩突然在QQ签名里写：“我想变胖啊！”  你回什么她会爱上你？(对话实例) - 成真恋爱学"},{"title":"女生为什么疏远你？这个问题很关键 - 成真恋爱学","date":"2019-09-07T04:06:58.397Z","excerpt":"","link":"2019/女生为什么疏远你？这个问题很关键 - 成真恋爱学"}]}